uliweb_ui/__init__.py
uliweb_ui/commands.py
uliweb_ui/gulp_settings.ini
uliweb_ui/gulpfile.js
uliweb_ui/settings.ini
uliweb_ui/doc/CHANGELOG.md
uliweb_ui/doc/ui_api.md
uliweb_ui/src/tags/editor.js
uliweb_ui/src/tags/pagination.tag
uliweb_ui/src/tags/query_condition.tag
uliweb_ui/src/tags/rgrid.tag
uliweb_ui/src/tags/rtable.tag
uliweb_ui/src/utils/css/chooser.css
uliweb_ui/src/utils/css/formb.css
uliweb_ui/src/utils/css/global.css
uliweb_ui/src/utils/css/pagination.css
uliweb_ui/src/utils/css/select2_fix.css
uliweb_ui/src/utils/js/async_block_message.js
uliweb_ui/src/utils/js/chooser.js
uliweb_ui/src/utils/js/clear_buttons.js
uliweb_ui/src/utils/js/common.js
uliweb_ui/src/utils/js/dialog.js
uliweb_ui/src/utils/js/formb.js
uliweb_ui/src/utils/js/pagination.js
uliweb_ui/src/utils/js/query_string.js
uliweb_ui/src/utils/js/tree_select.js
uliweb_ui/static/jsmodules.js
uliweb_ui/static/uliweb_ui_common.js
uliweb_ui/static/uliweb_ui_common_sub.css
uliweb_ui/static/uliweb_ui_common_sub.js
uliweb_ui/static/uliweb_ui_mmgrid.css
uliweb_ui/static/uliweb_ui_mmgrid.js
uliweb_ui/static/uliweb_ui_rtable.css
uliweb_ui/static/uliweb_ui_rtable.js
uliweb_ui/static/modules/bootstrap-filestyle.js
uliweb_ui/static/modules/dataset.js
uliweb_ui/static/modules/head.load.min.js
uliweb_ui/static/modules/jquery.blockUI.js
uliweb_ui/static/modules/jquery.form.js
uliweb_ui/static/modules/jquery.pjax.js
uliweb_ui/static/modules/json2.js
uliweb_ui/static/modules/moment-with-locales.min.js
uliweb_ui/static/modules/uliweb-ui.css
uliweb_ui/static/modules/uliweb-ui.js
uliweb_ui/static/modules/uliweb-ui.min.css
uliweb_ui/static/modules/uliweb-ui.min.js
uliweb_ui/static/modules/amcharts/amcharts.js
uliweb_ui/static/modules/amcharts/funnel.js
uliweb_ui/static/modules/amcharts/gantt.js
uliweb_ui/static/modules/amcharts/gauge.js
uliweb_ui/static/modules/amcharts/pie.js
uliweb_ui/static/modules/amcharts/radar.js
uliweb_ui/static/modules/amcharts/serial.js
uliweb_ui/static/modules/amcharts/xy.js
uliweb_ui-0.1.0.dist-info/METADATA
uliweb_ui-0.1.0.dist-info/WHEEL
uliweb_ui-0.1.0.dist-info/top_level.txt
uliweb_ui-0.1.0.dist-info/RECORD
